[
  {
    "id": "Timeline 6",
    "captions": [
      "fr",
      "en"
    ],
    "formats_generated": [
      "16x9",
      "9x16",
      "1x1"
    ],
    "bunny_urls": {
      "16x9": "https://vz-72668a20-6b9.b-cdn.net/560c6aab-c0db-4d9b-a8ee-693fe0d38c22/play_720p.mp4",
      "9x16": "https://vz-72668a20-6b9.b-cdn.net/2a9edca0-80d2-4427-8cc9-2be7fe4383ab/play_720p.mp4",
      "1x1": "https://vz-72668a20-6b9.b-cdn.net/f61d7d1a-6dea-4ce2-a559-c3e51207f3d0/play_720p.mp4"
    },
    "updated_at": "2026-01-19T22:26:13.435069Z"
  },
  {
    "id": "Timeline 5",
    "captions": [
      "fr",
      "en"
    ],
    "formats_generated": [
      "16x9",
      "9x16",
      "1x1"
    ],
    "bunny_urls": {
      "16x9": "https://vz-72668a20-6b9.b-cdn.net/8422cd47-fd0b-4ac7-8abe-03610e487e88/play_720p.mp4",
      "9x16": "https://vz-72668a20-6b9.b-cdn.net/b68febe3-1167-4c7e-be72-47e07c0a3de0/play_720p.mp4",
      "1x1": "https://vz-72668a20-6b9.b-cdn.net/32b7a87c-1d6b-4994-9473-c85d4a845a24/play_720p.mp4"
    },
    "updated_at": "2026-01-19T22:26:06.413760Z"
  },
  {
    "id": "Timeline 4",
    "captions": [
      "fr",
      "en"
    ],
    "formats_generated": [
      "16x9",
      "9x16",
      "1x1"
    ],
    "bunny_urls": {
      "16x9": "https://vz-INVALID.b-cdn.net/46e679cf-30fa-498b-8a2c-87ae92eca174/play_720p.mp4",
      "9x16": "https://vz-INVALID.b-cdn.net/6828cd2c-4e3e-4d63-a154-5b524be07ffe/play_720p.mp4",
      "1x1": "https://vz-INVALID.b-cdn.net/532bb46b-08e8-4f78-b178-7323ce939d64/play_720p.mp4"
    },
    "updated_at": "2026-01-19T18:34:39.383058Z"
  },
  {
    "id": "grok-video-ccd422af-770a-41b7-9298-868a89d8599c",
    "captions": [
      "fr",
      "en"
    ],
    "formats_generated": [
      "16x9",
      "9x16"
    ],
    "bunny_urls": {
      "16x9": "https://vz-INVALID.b-cdn.net/40d113c6-659c-41e5-bf81-b1ca1b347d1b/play_720p.mp4",
      "9x16": "https://vz-INVALID.b-cdn.net/94db88cf-eb99-4d4b-a4de-ab9580c1d39f/play_720p.mp4"
    },
    "updated_at": "2026-01-19T18:17:51.553088Z"
  },
  {
    "id": "new",
    "captions": [
      "fr",
      "en"
    ],
    "formats_generated": [
      "16x9",
      "9x16"
    ],
    "bunny_urls": {
      "16x9": "https://vz-INVALID.b-cdn.net/c984e248-9a90-4b03-99e3-fe9a95ba804d/play_720p.mp4",
      "9x16": "https://vz-INVALID.b-cdn.net/fdb32c20-e1d3-48cc-a9bd-0e7ae3cab249/play_720p.mp4"
    },
    "updated_at": "2026-01-19T18:17:47.878820Z"
  },
  {
    "id": "2026-01-15-solo-tease-silent",
    "captions": [
      "fr",
      "en"
    ],
    "formats_generated": [
      "16x9",
      "9x16"
    ],
    "bunny_urls": {
      "16x9": "https://vz-INVALID.b-cdn.net/54ca5217-a757-4b3a-8fc4-91175a101367/play_720p.mp4",
      "9x16": "https://vz-INVALID.b-cdn.net/67197e1d-8228-4649-8f60-48020e4ba6ed/play_720p.mp4"
    },
    "updated_at": "2026-01-19T18:17:43.941005Z"
  },
  {
    "id": "allons-y-encore",
    "captions": [
      "fr",
      "en"
    ],
    "formats_generated": [
      "16x9",
      "9x16"
    ],
    "bunny_urls": {
      "16x9": "https://iframe.mediadelivery.net/play/581630/4dc120a1-c599-42d6-8302-9c5e46227d2c",
      "9x16": "https://iframe.mediadelivery.net/play/581630/7c635586-0539-426a-9a11-a68d2e7d8fcc"
    },
    "updated_at": "2026-01-19T11:14:44.636900Z"
  },
  {
    "id": "allons-y-assez",
    "captions": [
      "fr",
      "en"
    ],
    "formats_generated": [
      "16x9",
      "9x16"
    ],
    "bunny_urls": {
      "16x9": "https://iframe.mediadelivery.net/play/581630/56ac4df7-2207-4377-92fb-cbcff2d515eb",
      "9x16": "https://iframe.mediadelivery.net/play/581630/ac2914f3-1971-489f-bf20-98a52f0dacf2"
    },
    "updated_at": "2026-01-19T11:14:07.452600Z"
  },
  {
    "id": "allons-y-finalement",
    "captions": [
      "fr",
      "en"
    ],
    "formats_generated": [
      "16x9",
      "9x16"
    ],
    "bunny_urls": {
      "16x9": "https://iframe.mediadelivery.net/play/581630/51334c55-b5c3-4335-a8e2-ad5491dafbb1",
      "9x16": "https://iframe.mediadelivery.net/play/581630/b9f255db-2508-47b9-a47d-90e2f4131e81"
    },
    "updated_at": "2026-01-19T11:13:43.667557Z"
  }
]